deeptoolkit/__init__.py
deeptoolkit/data.py
deeptoolkit/evaluation.py
deeptoolkit/losses.py
deeptoolkit/blocks/__init__.py
deeptoolkit/blocks/applied.py
deeptoolkit/blocks/generic.py
deeptoolkit/blocks/hybrid.py
deeptoolkit/core/__init__.py
deeptoolkit/core/functional.py
deeptoolkit/internal/__init__.py
deeptoolkit/internal/acquisition.py
deeptoolkit/internal/beautification.py
deeptoolkit/internal/conversion.py
deeptoolkit/internal/helpers.py
deeptoolkit/internal/validation.py
deeptoolkit/vision/__init__.py
deeptoolkit/vision/face_detector.py
deeptoolkit-0.2.1.dist-info/LICENSE
deeptoolkit-0.2.1.dist-info/METADATA
deeptoolkit-0.2.1.dist-info/WHEEL
deeptoolkit-0.2.1.dist-info/top_level.txt
deeptoolkit-0.2.1.dist-info/RECORD
