Metadata-Version: 2.1
Name: deeptoolkit
Version: 0.2.1
Summary: A deep learning library containing implementations of popular algorithms and extensions to TensorFlow and Keras.
Home-page: https://github.com/amogh7joshi/deeptoolkit
Author: Amogh Joshi
Author-email: joshi.amoghn@gmail.com
License: MIT
Platform: UNKNOWN
Classifier: License :: OSI Approved :: MIT License
Classifier: Programming Language :: Python :: 3
Classifier: Operating System :: OS Independent
